bact_archiver/carchiver.py
bact_archiver/epics_event.cpython-310-x86_64-linux-gnu.so
bact_archiver/config.py
bact_archiver/errors.py
bact_archiver/__init__.py
bact_archiver/register.py
bact_archiver/archiver.py
bact_archiver/pyarchiver.py
bact_archiver/epics_event_pb2.py
bact_archiver/protocol_buffer.py
bact_archiver-0.1.0.dist-info/METADATA
bact_archiver-0.1.0.dist-info/RECORD
bact_archiver-0.1.0.dist-info/WHEEL
bact_archiver-0.1.0.dist-info/top_level.txt
bact_archiver-0.1.0.dist-info/LICENSE
proto/epics_event.pyx
proto/epics_event.proto
proto/__init__.py
proto/epics_event.pxd
proto/epics_event.cpp
bact_archiver-0.1.0.data/data/config/archiver.cfg
