Metadata-Version: 2.1
Name: bact-archiver
Version: 0.1.0
Summary: EPICS archiver appliance access using google protobuf
Home-page: https://github.com/hz-b/bact-archiver
Author: Andreas Schälicke, Pierre Schnizer
Author-email: andreas.schaelicke@helmholtz-berlin.de, pierre.schnizer@helmholtz-berlin.de
Classifier: Development Status :: 4 - Beta
Classifier: Intended Audience :: Science/Research
Classifier: License :: OSI Approved :: GNU General Public License (GPL)
Classifier: Programming Language :: Python :: 3
Classifier: Topic :: Scientific/Engineering :: Physics
License-File: LICENSE
Provides-Extra: dev
Requires-Dist: cython ; extra == 'dev'
